employeeaccount/__init__.py
employeeaccount/employeeAccount.py
employeeaccount-1.0.0.dist-info/LICENSE.txt
employeeaccount-1.0.0.dist-info/METADATA
employeeaccount-1.0.0.dist-info/WHEEL
employeeaccount-1.0.0.dist-info/top_level.txt
employeeaccount-1.0.0.dist-info/RECORD
