Metadata-Version: 2.1
Name: employeeaccount
Version: 1.0.0
Summary: An awesome package that does something
Home-page: http://pypi.python.org/pypi/employeeaccount/
Author: bkhaldi
Author-email: b.khaldi@esi-sba.dz
License: LICENSE.txt
License-File: LICENSE.txt
Requires-Dist: employeeaccount
